{
  "auto_turret": {
    "gunpowder": 0,
    "metal": 140,
    "Cementing Pasta": 50,
    "polymer": 20,
    "electronics": 70,
    "Silica Pearls": 0,
    "element": 0
  },
  "heavy_turret": {
    "gunpowder": 0,
    "metal": 400,
    "Cementing Pasta": 150,
    "polymer": 50,
    "electronics": 200,
    "Silica Pearls": 0,
    "element": 0
  },
  "tek_turret": {
    "gunpowder": 0,
    "metal": 100,
    "Cementing Pasta": 50,
    "polymer": 50,
    "electronics": 100,
    "Silica Pearls": 0,
    "element": 3
  },
  "advanced_bullet": {
    "gunpowder": 18,
    "metal": 2,
    "Cementing Pasta": 0,
    "polymer": 0,
    "electronics": 0,
    "Silica Pearls": 0,
    "element": 0
  },
  "electronics": {
    "Silica Pearls": 0,
    "metal": 0
  },
  "element_shard": {
    "element": 0.01
  },
  "double_doorframe": {
    "metal": 20,
    "Cementing Pasta": 6
  },
  "giant_metal_hatchframe": {
    "metal": 240,
    "Cementing Pasta": 64
  },
  "metal_foundation": {
    "metal": 50,
    "Cementing Pasta": 15
  }
}
